mtabe/__init__.py
mtabe/bots.py
mtabe/config.py
mtabe/main.py
mtabe/reader.py
mtabe/t.py
mtabe/youtube_sbt.py
mtabe/bots/__init__.py
mtabe/bots/bots.py
mtabe/config/__init__.py
mtabe/config/config.py
mtabe/reader/__init__.py
mtabe/reader/reader.py
mtabe/youtube/__init__.py
mtabe/youtube/youtube_sbt.py
mtabe-1.9.0.dist-info/METADATA
mtabe-1.9.0.dist-info/WHEEL
mtabe-1.9.0.dist-info/entry_points.txt
mtabe-1.9.0.dist-info/top_level.txt
mtabe-1.9.0.dist-info/RECORD
