Metadata-Version: 2.4
Name: mtabe
Version: 1.9.0
Summary: An AI-powered CLI for adding notes and generating flashcards, tests, and chat summaries.
Home-page: https://github.com/Henryle-hd/mtabe
Author: Henrylee
Author-email: henrydionizi@gmail.com
Keywords: cli ai notes flashcards
Classifier: Programming Language :: Python :: 3
Classifier: License :: OSI Approved :: MIT License
Classifier: Operating System :: OS Independent
Requires-Python: >=3.8
Requires-Dist: click<9.0,>=8.1.8
Requires-Dist: colorama<0.5,>=0.4.6
Requires-Dist: rich<15.0,>=14.0.0
Requires-Dist: pandas<3.0,>=2.2.3
Requires-Dist: openpyxl<4.0,>=3.1.5
Requires-Dist: xlrd<3.0,>=2.0.1
Requires-Dist: python-docx<2.0,>=1.1.2
Requires-Dist: PyPDF2<4.0,>=3.0.1
Requires-Dist: python-pptx<2.0,>=1.0.2
Requires-Dist: requests<3.0,>=2.32.3
Requires-Dist: beautifulsoup4<5.0,>=4.13.4
Requires-Dist: pyfiglet<2.0,>=1.0.2
Requires-Dist: python-dotenv<2.0,>=1.1.0
Requires-Dist: groq<1.0,>=0.23.1
Requires-Dist: yt-dlp<2026.0,>=2025.5.22
Dynamic: author
Dynamic: author-email
Dynamic: classifier
Dynamic: description
Dynamic: description-content-type
Dynamic: home-page
Dynamic: keywords
Dynamic: requires-dist
Dynamic: requires-python
Dynamic: summary
